restrictedboosting
